.gitignore
.travis.yml
LICENSE
README.rst
setup.py
metis/__init__.py
metis/__main__.py
metis/camera.py
metis/led.py
metis/motion.py
metis/telegram.py
metispi.egg-info/PKG-INFO
metispi.egg-info/SOURCES.txt
metispi.egg-info/dependency_links.txt
metispi.egg-info/requires.txt
metispi.egg-info/top_level.txt