Metadata-Version: 1.0
Name: metispi
Version: 0.1.1
Summary: In brightest day in blackest night no evil shall escape your sight!
Home-page: https://github.com/olha-kurkaiedova/metis
Author: Olha Kurkaiedova
Author-email: olya.kurkaedova@gmail.com
License: MIT
Keywords: RaspberryPi RPi motion sensor
Platform: UNKNOWN
